labella/__init__.py
labella/__version__.py
labella/d3_time.py
labella/distributor.py
labella/force.py
labella/metrics.py
labella/node.py
labella/removeOverlap.py
labella/renderer.py
labella/scale.py
labella/tex.py
labella/timeline.py
labella/utils.py
labella/vpsc.py
labella-0.9.8.dist-info/LICENSE
labella-0.9.8.dist-info/METADATA
labella-0.9.8.dist-info/WHEEL
labella-0.9.8.dist-info/top_level.txt
labella-0.9.8.dist-info/RECORD
