Metadata-Version: 2.1
Name: labella
Version: 0.9.8
Summary: Python clone of Labella.js that supports TikZ output
Home-page: https://github.com/GjjvdBurg/labella.py
Author: Gertjan van den Burg
Author-email: gertjanvandenburg@gmail.com
License: Apache-2.0
Platform: UNKNOWN
Classifier: License :: OSI Approved :: MIT License
Classifier: Programming Language :: Python
Classifier: Programming Language :: Python :: 3
Classifier: Programming Language :: Python :: 3.5
Classifier: Programming Language :: Python :: 3.6
Classifier: Programming Language :: Python :: 3.7
Classifier: Programming Language :: Python :: Implementation :: CPython
Classifier: Programming Language :: Python :: Implementation :: PyPy
Requires-Python: >=3.5.0
Requires-Dist: intervaltree (>=3.0.0)
Provides-Extra: dev
Requires-Dist: green ; extra == 'dev'
Provides-Extra: docs
Provides-Extra: tests
